<?xml version="1.0" encoding="UTF-8" standalone="no"?>
<Despesas>
  <Despesa>
    <nome>Livro java</nome>
    <nomeGrupo>mc322</nomeGrupo>
    <data>jun. 13</data>
    <valor>50.0</valor>
    <pagante>
      <nomePagante>ciclano</nomePagante>
      <saldo>33.33333333333333</saldo>
    </pagante>
    <devedores>
      <devedor>
        <nomeDevedor>abc</nomeDevedor>
        <saldo>-16.666666666666668</saldo>
      </devedor>
      <devedor>
        <nomeDevedor>ciclano</nomeDevedor>
        <saldo>-16.666666666666668</saldo>
      </devedor>
      <devedor>
        <nomeDevedor>beltrano</nomeDevedor>
        <saldo>-16.666666666666668</saldo>
      </devedor>
    </devedores>
    <quitada>false</quitada>
  </Despesa>
</Despesas>
